edilkamin/__init__.py
edilkamin/__main__.py
edilkamin/api.py
edilkamin/async_dispatch.py
edilkamin/ble.py
edilkamin/buffer_utils.py
edilkamin/constants.py
edilkamin/utils.py
edilkamin-1.6.0.dist-info/licenses/LICENSE
edilkamin-1.6.0.dist-info/METADATA
edilkamin-1.6.0.dist-info/WHEEL
edilkamin-1.6.0.dist-info/entry_points.txt
edilkamin-1.6.0.dist-info/top_level.txt
edilkamin-1.6.0.dist-info/RECORD
