Metadata-Version: 2.4
Name: edilkamin
Version: 1.6.0
Summary: Edilkamin Stove Python client
Author: Andre Miras
Project-URL: Homepage, https://github.com/AndreMiras/edilkamin.py
Requires-Python: >=3.10
License-File: LICENSE
Requires-Dist: anyio
Requires-Dist: httpx
Requires-Dist: pycognito
Provides-Extra: ble
Requires-Dist: simplepyble; extra == "ble"
Provides-Extra: dev
Requires-Dist: build; extra == "dev"
Requires-Dist: coveralls; extra == "dev"
Requires-Dist: pytest; extra == "dev"
Requires-Dist: pytest-asyncio; extra == "dev"
Requires-Dist: pytest-cov; extra == "dev"
Requires-Dist: ruff; extra == "dev"
Requires-Dist: tox; extra == "dev"
Requires-Dist: twine; extra == "dev"
Requires-Dist: wheel; extra == "dev"
Requires-Dist: respx; extra == "dev"
Provides-Extra: doc
Requires-Dist: myst-parser; extra == "doc"
Requires-Dist: sphinx; extra == "doc"
Requires-Dist: sphinx-rtd-theme; extra == "doc"
Dynamic: license-file
